{
  "name": "obs.js",
  "repo": "pluma/obs.js",
  "description": "Observable properties done right.",
  "keywords": [
    "observable",
    "properties"
  ],
  "version": "0.5.1",
  "dependencies": {
    "jgallen23/aug": "0.0.5",
    "pluma/sublish": "0.4.1"
  },
  "devDependencies": {
    "mocha": "1.7.x",
    "expect": "0.2.x",
    "uglify-js": "1.3.x"
  },
  "scripts": ["dist/obs.js"],
  "main": "./dist/obs.js",
  "ignore":  [
    "**/.*",
    "build",
    "components",
    "node_modules"
  ],
  "license": "MIT"
}
